ptapi42/__init__.py
ptapi42/api42.py
ptapi42/api42_token.py
ptapi42/config.py
ptapi42-1.0.6.dist-info/LICENSE
ptapi42-1.0.6.dist-info/METADATA
ptapi42-1.0.6.dist-info/WHEEL
ptapi42-1.0.6.dist-info/top_level.txt
ptapi42-1.0.6.dist-info/RECORD
