Metadata-Version: 2.2
Name: ptapi42
Version: 1.0.6
Summary: A python package that simplifies the process of making API requests to 42's API.
Author: 42 Portugal
Author-email: root@42porto.com
License: MIT License
Project-URL: repository, https://github.com/42-Portugal/ptapi42
Project-URL: Bug Tracker, https://github.com/42-Portugal/ptapi42/issues
Classifier: Programming Language :: Python :: 3
Classifier: License :: OSI Approved :: MIT License
Classifier: Operating System :: OS Independent
Requires-Python: >=3.7
License-File: LICENSE
